src/__init__.py
src/tahvil_hesaplamalari.py
tahvil_hesaplamalari-1.0.0.dist-info/METADATA
tahvil_hesaplamalari-1.0.0.dist-info/WHEEL
tahvil_hesaplamalari-1.0.0.dist-info/top_level.txt
tahvil_hesaplamalari-1.0.0.dist-info/RECORD
